[
  {
    "id": "preset_1767915765988_u7si6em",
    "userId": "usr_1767825506370_0v10k3s",
    "name": "bánh mì",
    "amount": 15000,
    "currency": "VND",
    "category": "FOOD",
    "notes": "bánh mì 2 trứng",
    "createdAt": "2026-01-08T23:42:45.988Z",
    "updatedAt": "2026-01-13T01:54:37.433Z"
  },
  {
    "id": "preset_1767915851190_rw8gsvw",
    "userId": "usr_1767825506370_0v10k3s",
    "name": "nước mía",
    "amount": 10000,
    "currency": "VND",
    "category": "FOOD",
    "notes": "",
    "createdAt": "2026-01-08T23:44:11.190Z",
    "updatedAt": "2026-01-08T23:44:11.190Z"
  },
  {
    "id": "preset_1768269269286_0325v04",
    "userId": "usr_1767825506370_0v10k3s",
    "name": "cafe sữa",
    "amount": 15000,
    "currency": "VND",
    "category": "FOOD",
    "notes": "",
    "createdAt": "2026-01-13T01:54:29.286Z",
    "updatedAt": "2026-01-13T01:55:14.380Z"
  },
  {
    "id": "preset_1768269299285_x5m3irn",
    "userId": "usr_1767825506370_0v10k3s",
    "name": "bánh mì trứng",
    "amount": 20000,
    "currency": "VND",
    "category": "FOOD",
    "notes": "",
    "createdAt": "2026-01-13T01:54:59.285Z",
    "updatedAt": "2026-01-13T01:54:59.285Z"
  }
]